{"id":"eaf04d537899fc767af855368f94d1759d34e2bf","url":"http://localhost:5173/src/router/index.js?t=1776546422749","source":"import { createRouter, createWebHistory } from \"/node_modules/.vite/deps/vue-router.js?v=89eb77fd\"\r\n\r\nconst routes = [\r\n    {\r\n        path: '/',\r\n        name: 'Home',\r\n        component: () => import(\"/src/views/Home.vue\")\r\n    },\r\n    {\r\n        path: '/engine_loader',\r\n        name: 'EngineLoader',\r\n        component: () => import(\"/src/views/EngineLoader.vue\")\r\n    },\r\n    {\r\n        path: '/cookie_policy',\r\n        name: 'CookiePolicy',\r\n        component: () => import(\"/src/views/CookiePolicy.vue\")\r\n    },\r\n    {\r\n        path: '/legal_notice',\r\n        name: 'LegalNotice',\r\n        component: () => import(\"/src/views/LegalNotice.vue\")\r\n    },\r\n    {\r\n        path: '/terms',\r\n        name: 'TermsOfService',\r\n        component: () => import(\"/src/views/TermsOfService.vue\")\r\n    },\r\n    {\r\n        path: '/magnetic_tool',\r\n        name: 'MagneticTool',\r\n        component: () => import(\"/src/views/MagneticTool.vue\")\r\n    },\r\n    {\r\n        path: '/insulation_adviser',\r\n        name: 'InsulationAdviser',\r\n        component: () => import(\"/src/views/InsulationAdviser.vue\")\r\n    },\r\n\r\n\r\n    {\r\n        path: '/catalog_tool',\r\n        name: 'CatalogTool',\r\n        component: () => import(\"/src/views/CatalogTool.vue\")\r\n    },\r\n    {\r\n        path: '/catalog',\r\n        name: 'Catalog',\r\n        component: () => import(\"/src/views/Catalog.vue\")\r\n    },\r\n    {\r\n        path: '/magnetic_viewer',\r\n        name: 'MagneticViewer',\r\n        component: () => import(\"/src/views/MagneticViewer.vue\")\r\n    },\r\n\r\n    {\r\n        path: '/wizards',\r\n        name: 'Wizards',\r\n        component: () => import(\"/src/views/Wizards.vue?t=1776546422749\")\r\n    },\r\n    {\r\n        path: '/wizards_landing',\r\n        name: 'WizardsLanding',\r\n        component: () => import(\"/src/views/WizardsLanding.vue\")\r\n    },\r\n\r\n\r\n    // {\r\n    //     path: '/dune',\r\n    //     name: 'Dune',\r\n    //     component: () => import('../views/Dune.vue')\r\n    // },\r\n    {\r\n        path: '/cross_referencer_selection',\r\n        name: 'CrossReferencerSelection',\r\n        component: () => import(\"/src/views/CrossReferencerSelections/CrossReferencerSelectionFairRite.vue\")\r\n    },\r\n    {\r\n        path: '/core_cross_referencer_fair_rite',\r\n        name: 'CoreCrossReferencerFairRite',\r\n        component: () => import(\"/src/views/CrossReferencers/CrossReferencerFairRite.vue\")\r\n    },\r\n    {\r\n        path: '/core_material_cross_referencer_fair_rite',\r\n        name: 'CoreMaterialCrossReferencerFairRite',\r\n        component: () => import(\"/src/views/CrossReferencers/CrossReferencerFairRite.vue\")\r\n    },\r\n    {\r\n        path: '/core_shape_cross_referencer_fair_rite',\r\n        name: 'CoreShapeCrossReferencerFairRite',\r\n        component: () => import(\"/src/views/CrossReferencers/CrossReferencerFairRite.vue\")\r\n    },\r\n    {\r\n        path: '/core_cross_referencer',\r\n        name: 'CoreCrossReferencer',\r\n        component: () => import(\"/src/views/CrossReferencers/CrossReferencer.vue\")\r\n    },\r\n    {\r\n        path: '/core_material_cross_referencer',\r\n        name: 'CoreMaterialCrossReferencer',\r\n        component: () => import(\"/src/views/CrossReferencers/CrossReferencer.vue\")\r\n    },\r\n    {\r\n        path: '/core_shape_cross_referencer',\r\n        name: 'CoreShapeCrossReferencer',\r\n        component: () => import(\"/src/views/CrossReferencers/CrossReferencer.vue\")\r\n    },\r\n\r\n]\r\nconst router = createRouter({\r\n    history: createWebHistory(),\r\n    routes,\r\n});\r\n\r\n\r\nexport default router\r","sourceMap":{"version":3,"sources":["index.js"],"sourcesContent":["import { createRouter, createWebHistory } from \"/node_modules/.vite/deps/vue-router.js?v=89eb77fd\"\r\n\r\nconst routes = [\r\n    {\r\n        path: '/',\r\n        name: 'Home',\r\n        component: () => import(\"/src/views/Home.vue\")\r\n    },\r\n    {\r\n        path: '/engine_loader',\r\n        name: 'EngineLoader',\r\n        component: () => import(\"/src/views/EngineLoader.vue\")\r\n    },\r\n    {\r\n        path: '/cookie_policy',\r\n        name: 'CookiePolicy',\r\n        component: () => import(\"/src/views/CookiePolicy.vue\")\r\n    },\r\n    {\r\n        path: '/legal_notice',\r\n        name: 'LegalNotice',\r\n        component: () => import(\"/src/views/LegalNotice.vue\")\r\n    },\r\n    {\r\n        path: '/terms',\r\n        name: 'TermsOfService',\r\n        component: () => import(\"/src/views/TermsOfService.vue\")\r\n    },\r\n    {\r\n        path: '/magnetic_tool',\r\n        name: 'MagneticTool',\r\n        component: () => import(\"/src/views/MagneticTool.vue\")\r\n    },\r\n    {\r\n        path: '/insulation_adviser',\r\n        name: 'InsulationAdviser',\r\n        component: () => import(\"/src/views/InsulationAdviser.vue\")\r\n    },\r\n\r\n\r\n    {\r\n        path: '/catalog_tool',\r\n        name: 'CatalogTool',\r\n        component: () => import(\"/src/views/CatalogTool.vue\")\r\n    },\r\n    {\r\n        path: '/catalog',\r\n        name: 'Catalog',\r\n        component: () => import(\"/src/views/Catalog.vue\")\r\n    },\r\n    {\r\n        path: '/magnetic_viewer',\r\n        name: 'MagneticViewer',\r\n        component: () => import(\"/src/views/MagneticViewer.vue\")\r\n    },\r\n\r\n    {\r\n        path: '/wizards',\r\n        name: 'Wizards',\r\n        component: () => import(\"/src/views/Wizards.vue?t=1776546422749\")\r\n    },\r\n    {\r\n        path: '/wizards_landing',\r\n        name: 'WizardsLanding',\r\n        component: () => import(\"/src/views/WizardsLanding.vue\")\r\n    },\r\n\r\n\r\n    // {\r\n    //     path: '/dune',\r\n    //     name: 'Dune',\r\n    //     component: () => import('../views/Dune.vue')\r\n    // },\r\n    {\r\n        path: '/cross_referencer_selection',\r\n        name: 'CrossReferencerSelection',\r\n        component: () => import(\"/src/views/CrossReferencerSelections/CrossReferencerSelectionFairRite.vue\")\r\n    },\r\n    {\r\n        path: '/core_cross_referencer_fair_rite',\r\n        name: 'CoreCrossReferencerFairRite',\r\n        component: () => import(\"/src/views/CrossReferencers/CrossReferencerFairRite.vue\")\r\n    },\r\n    {\r\n        path: '/core_material_cross_referencer_fair_rite',\r\n        name: 'CoreMaterialCrossReferencerFairRite',\r\n        component: () => import(\"/src/views/CrossReferencers/CrossReferencerFairRite.vue\")\r\n    },\r\n    {\r\n        path: '/core_shape_cross_referencer_fair_rite',\r\n        name: 'CoreShapeCrossReferencerFairRite',\r\n        component: () => import(\"/src/views/CrossReferencers/CrossReferencerFairRite.vue\")\r\n    },\r\n    {\r\n        path: '/core_cross_referencer',\r\n        name: 'CoreCrossReferencer',\r\n        component: () => import(\"/src/views/CrossReferencers/CrossReferencer.vue\")\r\n    },\r\n    {\r\n        path: '/core_material_cross_referencer',\r\n        name: 'CoreMaterialCrossReferencer',\r\n        component: () => import(\"/src/views/CrossReferencers/CrossReferencer.vue\")\r\n    },\r\n    {\r\n        path: '/core_shape_cross_referencer',\r\n        name: 'CoreShapeCrossReferencer',\r\n        component: () => import(\"/src/views/CrossReferencers/CrossReferencer.vue\")\r\n    },\r\n\r\n]\r\nconst router = createRouter({\r\n    history: createWebHistory(),\r\n    routes,\r\n});\r\n\r\n\r\nexport default router\r\n"],"names":[],"mappings":"AAAA,MAAM,CAAC,CAAC,CAAC,YAAY,CAAC,CAAC,gBAAgB,CAAC,CAAC,CAAC,IAAI,CAAC,CAAC,CAAC,YAAY,CAAC,CAAC,IAAI,CAAC,IAAI,CAAC,GAAG,CAAC,MAAM,CAAC,EAAE,CAAC,CAAC,CAAC,QAAQ,CAAC;AAClG;AACA,KAAK,CAAC,MAAM,CAAC,CAAC,CAAC,CAAC;AAChB,CAAC,CAAC,CAAC,CAAC,CAAC;AACL,CAAC,CAAC,CAAC,CAAC,CAAC,CAAC,CAAC,CAAC,IAAI,CAAC,CAAC,CAAC,CAAC,CAAC,CAAC;AAClB,CAAC,CAAC,CAAC,CAAC,CAAC,CAAC,CAAC,CAAC,IAAI,CAAC,CAAC,CAAC,IAAI,CAAC,CAAC;AACrB,CAAC,CAAC,CAAC,CAAC,CAAC,CAAC,CAAC,CAAC,SAAS,CAAC,CAAC,CAAC,CAAC,CAAC,CAAC,CAAC,CAAC,MAAM,CAAC,CAAC,CAAC,GAAG,CAAC,KAAK,CAAC,IAAI,CAAC,GAAG,CAAC,CAAC;AACtD,CAAC,CAAC,CAAC,CAAC,CAAC,CAAC;AACN,CAAC,CAAC,CAAC,CAAC,CAAC;AACL,CAAC,CAAC,CAAC,CAAC,CAAC,CAAC,CAAC,CAAC,IAAI,CAAC,CAAC,CAAC,CAAC,aAAa,CAAC,CAAC;AAC/B,CAAC,CAAC,CAAC,CAAC,CAAC,CAAC,CAAC,CAAC,IAAI,CAAC,CAAC,CAAC,YAAY,CAAC,CAAC;AAC7B,CAAC,CAAC,CAAC,CAAC,CAAC,CAAC,CAAC,CAAC,SAAS,CAAC,CAAC,CAAC,CAAC,CAAC,CAAC,CAAC,CAAC,MAAM,CAAC,CAAC,CAAC,GAAG,CAAC,KAAK,CAAC,YAAY,CAAC,GAAG,CAAC,CAAC;AAC9D,CAAC,CAAC,CAAC,CAAC,CAAC,CAAC;AACN,CAAC,CAAC,CAAC,CAAC,CAAC;AACL,CAAC,CAAC,CAAC,CAAC,CAAC,CAAC,CAAC,CAAC,IAAI,CAAC,CAAC,CAAC,CAAC,aAAa,CAAC,CAAC;AAC/B,CAAC,CAAC,CAAC,CAAC,CAAC,CAAC,CAAC,CAAC,IAAI,CAAC,CAAC,CAAC,YAAY,CAAC,CAAC;AAC7B,CAAC,CAAC,CAAC,CAAC,CAAC,CAAC,CAAC,CAAC,SAAS,CAAC,CAAC,CAAC,CAAC,CAAC,CAAC,CAAC,CAAC,MAAM,CAAC,CAAC,CAAC,GAAG,CAAC,KAAK,CAAC,YAAY,CAAC,GAAG,CAAC,CAAC;AAC9D,CAAC,CAAC,CAAC,CAAC,CAAC,CAAC;AACN,CAAC,CAAC,CAAC,CAAC,CAAC;AACL,CAAC,CAAC,CAAC,CAAC,CAAC,CAAC,CAAC,CAAC,IAAI,CAAC,CAAC,CAAC,CAAC,YAAY,CAAC,CAAC;AAC9B,CAAC,CAAC,CAAC,CAAC,CAAC,CAAC,CAAC,CAAC,IAAI,CAAC,CAAC,CAAC,WAAW,CAAC,CAAC;AAC5B,CAAC,CAAC,CAAC,CAAC,CAAC,CAAC,CAAC,CAAC,SAAS,CAAC,CAAC,CAAC,CAAC,CAAC,CAAC,CAAC,CAAC,MAAM,CAAC,CAAC,CAAC,GAAG,CAAC,KAAK,CAAC,WAAW,CAAC,GAAG,CAAC,CAAC;AAC7D,CAAC,CAAC,CAAC,CAAC,CAAC,CAAC;AACN,CAAC,CAAC,CAAC,CAAC,CAAC;AACL,CAAC,CAAC,CAAC,CAAC,CAAC,CAAC,CAAC,CAAC,IAAI,CAAC,CAAC,CAAC,CAAC,KAAK,CAAC,CAAC;AACvB,CAAC,CAAC,CAAC,CAAC,CAAC,CAAC,CAAC,CAAC,IAAI,CAAC,CAAC,CAAC,cAAc,CAAC,CAAC;AAC/B,CAAC,CAAC,CAAC,CAAC,CAAC,CAAC,CAAC,CAAC,SAAS,CAAC,CAAC,CAAC,CAAC,CAAC,CAAC,CAAC,CAAC,MAAM,CAAC,CAAC,CAAC,GAAG,CAAC,KAAK,CAAC,cAAc,CAAC,GAAG,CAAC,CAAC;AAChE,CAAC,CAAC,CAAC,CAAC,CAAC,CAAC;AACN,CAAC,CAAC,CAAC,CAAC,CAAC;AACL,CAAC,CAAC,CAAC,CAAC,CAAC,CAAC,CAAC,CAAC,IAAI,CAAC,CAAC,CAAC,CAAC,aAAa,CAAC,CAAC;AAC/B,CAAC,CAAC,CAAC,CAAC,CAAC,CAAC,CAAC,CAAC,IAAI,CAAC,CAAC,CAAC,YAAY,CAAC,CAAC;AAC7B,CAAC,CAAC,CAAC,CAAC,CAAC,CAAC,CAAC,CAAC,SAAS,CAAC,CAAC,CAAC,CAAC,CAAC,CAAC,CAAC,CAAC,MAAM,CAAC,CAAC,CAAC,GAAG,CAAC,KAAK,CAAC,YAAY,CAAC,GAAG,CAAC,CAAC;AAC9D,CAAC,CAAC,CAAC,CAAC,CAAC,CAAC;AACN,CAAC,CAAC,CAAC,CAAC,CAAC;AACL,CAAC,CAAC,CAAC,CAAC,CAAC,CAAC,CAAC,CAAC,IAAI,CAAC,CAAC,CAAC,CAAC,kBAAkB,CAAC,CAAC;AACpC,CAAC,CAAC,CAAC,CAAC,CAAC,CAAC,CAAC,CAAC,IAAI,CAAC,CAAC,CAAC,iBAAiB,CAAC,CAAC;AAClC,CAAC,CAAC,CAAC,CAAC,CAAC,CAAC,CAAC,CAAC,SAAS,CAAC,CAAC,CAAC,CAAC,CAAC,CAAC,CAAC,CAAC,MAAM,CAAC,CAAC,CAAC,GAAG,CAAC,KAAK,CAAC,iBAAiB,CAAC,GAAG,CAAC,CAAC;AACnE,CAAC,CAAC,CAAC,CAAC,CAAC,CAAC;AACN;AACA;AACA,CAAC,CAAC,CAAC,CAAC,CAAC;AACL,CAAC,CAAC,CAAC,CAAC,CAAC,CAAC,CAAC,CAAC,IAAI,CAAC,CAAC,CAAC,CAAC,YAAY,CAAC,CAAC;AAC9B,CAAC,CAAC,CAAC,CAAC,CAAC,CAAC,CAAC,CAAC,IAAI,CAAC,CAAC,CAAC,WAAW,CAAC,CAAC;AAC5B,CAAC,CAAC,CAAC,CAAC,CAAC,CAAC,CAAC,CAAC,SAAS,CAAC,CAAC,CAAC,CAAC,CAAC,CAAC,CAAC,CAAC,MAAM,CAAC,CAAC,CAAC,GAAG,CAAC,KAAK,CAAC,WAAW,CAAC,GAAG,CAAC,CAAC;AAC7D,CAAC,CAAC,CAAC,CAAC,CAAC,CAAC;AACN,CAAC,CAAC,CAAC,CAAC,CAAC;AACL,CAAC,CAAC,CAAC,CAAC,CAAC,CAAC,CAAC,CAAC,IAAI,CAAC,CAAC,CAAC,CAAC,OAAO,CAAC,CAAC;AACzB,CAAC,CAAC,CAAC,CAAC,CAAC,CAAC,CAAC,CAAC,IAAI,CAAC,CAAC,CAAC,OAAO,CAAC,CAAC;AACxB,CAAC,CAAC,CAAC,CAAC,CAAC,CAAC,CAAC,CAAC,SAAS,CAAC,CAAC,CAAC,CAAC,CAAC,CAAC,CAAC,CAAC,MAAM,CAAC,CAAC,CAAC,GAAG,CAAC,KAAK,CAAC,OAAO,CAAC,GAAG,CAAC,CAAC;AACzD,CAAC,CAAC,CAAC,CAAC,CAAC,CAAC;AACN,CAAC,CAAC,CAAC,CAAC,CAAC;AACL,CAAC,CAAC,CAAC,CAAC,CAAC,CAAC,CAAC,CAAC,IAAI,CAAC,CAAC,CAAC,CAAC,eAAe,CAAC,CAAC;AACjC,CAAC,CAAC,CAAC,CAAC,CAAC,CAAC,CAAC,CAAC,IAAI,CAAC,CAAC,CAAC,cAAc,CAAC,CAAC;AAC/B,CAAC,CAAC,CAAC,CAAC,CAAC,CAAC,CAAC,CAAC,SAAS,CAAC,CAAC,CAAC,CAAC,CAAC,CAAC,CAAC,CAAC,MAAM,CAAC,CAAC,CAAC,GAAG,CAAC,KAAK,CAAC,cAAc,CAAC,GAAG,CAAC,CAAC;AAChE,CAAC,CAAC,CAAC,CAAC,CAAC,CAAC;AACN;AACA,CAAC,CAAC,CAAC,CAAC,CAAC;AACL,CAAC,CAAC,CAAC,CAAC,CAAC,CAAC,CAAC,CAAC,IAAI,CAAC,CAAC,CAAC,CAAC,OAAO,CAAC,CAAC;AACzB,CAAC,CAAC,CAAC,CAAC,CAAC,CAAC,CAAC,CAAC,IAAI,CAAC,CAAC,CAAC,OAAO,CAAC,CAAC;AACxB,CAAC,CAAC,CAAC,CAAC,CAAC,CAAC,CAAC,CAAC,SAAS,CAAC,CAAC,CAAC,CAAC,CAAC,CAAC,CAAC,CAAC,MAAM,CAAC,CAAC,CAAC,GAAG,CAAC,KAAK,CAAC,OAAO,CAAC,GAAG,CAAC,CAAC,CAAC,aAAa,CAAC,CAAC;AACzE,CAAC,CAAC,CAAC,CAAC,CAAC,CAAC;AACN,CAAC,CAAC,CAAC,CAAC,CAAC;AACL,CAAC,CAAC,CAAC,CAAC,CAAC,CAAC,CAAC,CAAC,IAAI,CAAC,CAAC,CAAC,CAAC,eAAe,CAAC,CAAC;AACjC,CAAC,CAAC,CAAC,CAAC,CAAC,CAAC,CAAC,CAAC,IAAI,CAAC,CAAC,CAAC,cAAc,CAAC,CAAC;AAC/B,CAAC,CAAC,CAAC,CAAC,CAAC,CAAC,CAAC,CAAC,SAAS,CAAC,CAAC,CAAC,CAAC,CAAC,CAAC,CAAC,CAAC,MAAM,CAAC,CAAC,CAAC,GAAG,CAAC,KAAK,CAAC,cAAc,CAAC,GAAG,CAAC,CAAC;AAChE,CAAC,CAAC,CAAC,CAAC,CAAC,CAAC;AACN;AACA;AACA,CAAC,CAAC,CAAC,CAAC,CAAC,CAAC,CAAC,CAAC;AACR,CAAC,CAAC,CAAC,CAAC,CAAC,CAAC,CAAC,CAAC,CAAC,CAAC,CAAC,IAAI,CAAC,CAAC,CAAC,CAAC,IAAI,CAAC,CAAC;AACzB,CAAC,CAAC,CAAC,CAAC,CAAC,CAAC,CAAC,CAAC,CAAC,CAAC,CAAC,IAAI,CAAC,CAAC,CAAC,IAAI,CAAC,CAAC;AACxB,CAAC,CAAC,CAAC,CAAC,CAAC,CAAC,CAAC,CAAC,CAAC,CAAC,CAAC,SAAS,CAAC,CAAC,CAAC,CAAC,CAAC,CAAC,CAAC,CAAC,MAAM,CAAC,CAAC,CAAC,CAAC,CAAC,KAAK,CAAC,IAAI,CAAC,GAAG,CAAC,CAAC;AACvD,CAAC,CAAC,CAAC,CAAC,CAAC,CAAC,CAAC,CAAC,CAAC;AACT,CAAC,CAAC,CAAC,CAAC,CAAC;AACL,CAAC,CAAC,CAAC,CAAC,CAAC,CAAC,CAAC,CAAC,IAAI,CAAC,CAAC,CAAC,CAAC,0BAA0B,CAAC,CAAC;AAC5C,CAAC,CAAC,CAAC,CAAC,CAAC,CAAC,CAAC,CAAC,IAAI,CAAC,CAAC,CAAC,wBAAwB,CAAC,CAAC;AACzC,CAAC,CAAC,CAAC,CAAC,CAAC,CAAC,CAAC,CAAC,SAAS,CAAC,CAAC,CAAC,CAAC,CAAC,CAAC,CAAC,CAAC,MAAM,CAAC,CAAC,CAAC,GAAG,CAAC,KAAK,CAAC,yBAAyB,CAAC,gCAAgC,CAAC,GAAG,CAAC,CAAC;AAC5G,CAAC,CAAC,CAAC,CAAC,CAAC,CAAC;AACN,CAAC,CAAC,CAAC,CAAC,CAAC;AACL,CAAC,CAAC,CAAC,CAAC,CAAC,CAAC,CAAC,CAAC,IAAI,CAAC,CAAC,CAAC,CAAC,+BAA+B,CAAC,CAAC;AACjD,CAAC,CAAC,CAAC,CAAC,CAAC,CAAC,CAAC,CAAC,IAAI,CAAC,CAAC,CAAC,2BAA2B,CAAC,CAAC;AAC5C,CAAC,CAAC,CAAC,CAAC,CAAC,CAAC,CAAC,CAAC,SAAS,CAAC,CAAC,CAAC,CAAC,CAAC,CAAC,CAAC,CAAC,MAAM,CAAC,CAAC,CAAC,GAAG,CAAC,KAAK,CAAC,gBAAgB,CAAC,uBAAuB,CAAC,GAAG,CAAC,CAAC;AAC1F,CAAC,CAAC,CAAC,CAAC,CAAC,CAAC;AACN,CAAC,CAAC,CAAC,CAAC,CAAC;AACL,CAAC,CAAC,CAAC,CAAC,CAAC,CAAC,CAAC,CAAC,IAAI,CAAC,CAAC,CAAC,CAAC,wCAAwC,CAAC,CAAC;AAC1D,CAAC,CAAC,CAAC,CAAC,CAAC,CAAC,CAAC,CAAC,IAAI,CAAC,CAAC,CAAC,mCAAmC,CAAC,CAAC;AACpD,CAAC,CAAC,CAAC,CAAC,CAAC,CAAC,CAAC,CAAC,SAAS,CAAC,CAAC,CAAC,CAAC,CAAC,CAAC,CAAC,CAAC,MAAM,CAAC,CAAC,CAAC,GAAG,CAAC,KAAK,CAAC,gBAAgB,CAAC,uBAAuB,CAAC,GAAG,CAAC,CAAC;AAC1F,CAAC,CAAC,CAAC,CAAC,CAAC,CAAC;AACN,CAAC,CAAC,CAAC,CAAC,CAAC;AACL,CAAC,CAAC,CAAC,CAAC,CAAC,CAAC,CAAC,CAAC,IAAI,CAAC,CAAC,CAAC,CAAC,qCAAqC,CAAC,CAAC;AACvD,CAAC,CAAC,CAAC,CAAC,CAAC,CAAC,CAAC,CAAC,IAAI,CAAC,CAAC,CAAC,gCAAgC,CAAC,CAAC;AACjD,CAAC,CAAC,CAAC,CAAC,CAAC,CAAC,CAAC,CAAC,SAAS,CAAC,CAAC,CAAC,CAAC,CAAC,CAAC,CAAC,CAAC,MAAM,CAAC,CAAC,CAAC,GAAG,CAAC,KAAK,CAAC,gBAAgB,CAAC,uBAAuB,CAAC,GAAG,CAAC,CAAC;AAC1F,CAAC,CAAC,CAAC,CAAC,CAAC,CAAC;AACN,CAAC,CAAC,CAAC,CAAC,CAAC;AACL,CAAC,CAAC,CAAC,CAAC,CAAC,CAAC,CAAC,CAAC,IAAI,CAAC,CAAC,CAAC,CAAC,qBAAqB,CAAC,CAAC;AACvC,CAAC,CAAC,CAAC,CAAC,CAAC,CAAC,CAAC,CAAC,IAAI,CAAC,CAAC,CAAC,mBAAmB,CAAC,CAAC;AACpC,CAAC,CAAC,CAAC,CAAC,CAAC,CAAC,CAAC,CAAC,SAAS,CAAC,CAAC,CAAC,CAAC,CAAC,CAAC,CAAC,CAAC,MAAM,CAAC,CAAC,CAAC,GAAG,CAAC,KAAK,CAAC,gBAAgB,CAAC,eAAe,CAAC,GAAG,CAAC,CAAC;AAClF,CAAC,CAAC,CAAC,CAAC,CAAC,CAAC;AACN,CAAC,CAAC,CAAC,CAAC,CAAC;AACL,CAAC,CAAC,CAAC,CAAC,CAAC,CAAC,CAAC,CAAC,IAAI,CAAC,CAAC,CAAC,CAAC,8BAA8B,CAAC,CAAC;AAChD,CAAC,CAAC,CAAC,CAAC,CAAC,CAAC,CAAC,CAAC,IAAI,CAAC,CAAC,CAAC,2BAA2B,CAAC,CAAC;AAC5C,CAAC,CAAC,CAAC,CAAC,CAAC,CAAC,CAAC,CAAC,SAAS,CAAC,CAAC,CAAC,CAAC,CAAC,CAAC,CAAC,CAAC,MAAM,CAAC,CAAC,CAAC,GAAG,CAAC,KAAK,CAAC,gBAAgB,CAAC,eAAe,CAAC,GAAG,CAAC,CAAC;AAClF,CAAC,CAAC,CAAC,CAAC,CAAC,CAAC;AACN,CAAC,CAAC,CAAC,CAAC,CAAC;AACL,CAAC,CAAC,CAAC,CAAC,CAAC,CAAC,CAAC,CAAC,IAAI,CAAC,CAAC,CAAC,CAAC,2BAA2B,CAAC,CAAC;AAC7C,CAAC,CAAC,CAAC,CAAC,CAAC,CAAC,CAAC,CAAC,IAAI,CAAC,CAAC,CAAC,wBAAwB,CAAC,CAAC;AACzC,CAAC,CAAC,CAAC,CAAC,CAAC,CAAC,CAAC,CAAC,SAAS,CAAC,CAAC,CAAC,CAAC,CAAC,CAAC,CAAC,CAAC,MAAM,CAAC,CAAC,CAAC,GAAG,CAAC,KAAK,CAAC,gBAAgB,CAAC,eAAe,CAAC,GAAG,CAAC,CAAC;AAClF,CAAC,CAAC,CAAC,CAAC,CAAC,CAAC;AACN;AACA,CAAC;AACD,KAAK,CAAC,MAAM,CAAC,CAAC,CAAC,YAAY,CAAC,CAAC;AAC7B,CAAC,CAAC,CAAC,CAAC,OAAO,CAAC,CAAC,gBAAgB,CAAC,CAAC,CAAC;AAChC,CAAC,CAAC,CAAC,CAAC,MAAM,CAAC;AACX,CAAC,CAAC,CAAC;AACH;AACA;AACA,MAAM,CAAC,OAAO,CAAC,MAAM;"}}